doctestprinter.py
doctestprinter-1.4.1.dist-info/LICENSE.md
doctestprinter-1.4.1.dist-info/METADATA
doctestprinter-1.4.1.dist-info/WHEEL
doctestprinter-1.4.1.dist-info/top_level.txt
doctestprinter-1.4.1.dist-info/RECORD
