Metadata-Version: 2.1
Name: doctestprinter
Version: 1.4.1
Summary: Helper functions to make fitting outputs for doctests.
Home-page: https://gitlab.com/david.scheliga/doctestprinter
Author: David Scheliga
License: GNU General Public License V3 (GPLv3)
Project-URL: Documentation, https://doctestprinter.readthedocs.io/en/latest/
Project-URL: Source Code Repository, https://gitlab.com/david.scheliga/doctestprinter
Keywords: doctest,helper,pandas
Platform: UNKNOWN
Classifier: Development Status :: 5 - Production/Stable
Classifier: License :: OSI Approved :: GNU General Public License v3 (GPLv3)
Classifier: Operating System :: OS Independent
Classifier: Programming Language :: Python
Classifier: Programming Language :: Python :: 3.6
Classifier: Programming Language :: Python :: 3.7
Classifier: Programming Language :: Python :: 3.8
Classifier: Programming Language :: Python :: 3.9
License-File: LICENSE.md
Requires-Dist: pandas (>=1.0.0)
Requires-Dist: numpy (>=1.16.0)
Requires-Dist: treenodedefinition (>=0.1)
